{
    "configurations": [
        {
            "name": "Linux",
            "browse": {
                "path": [
                    "${workspaceFolder}"
                ],
                "limitSymbolsToIncludedHeaders": true
            },
            "includePath": [
                "${workspaceFolder}",
                "/usr/include/qt4/QtGui",
                "/usr/include/qt/QtWidgets"
            ],
            "defines": [],
            "compilerPath": "/bin/clang",
            "cStandard": "c11",
            "cppStandard": "c++17",
            "intelliSenseMode": "clang-x64"
        }
    ],
    "version": 4
}